[{"condition": {"id": 1568}, "defaults": {"site_id": 66, "file_path": "layanan.jpg", "jenis": "highlight1", "created_at": "2022-01-11T13:18:01.579Z", "updated_at": "2022-01-11T13:18:01.579Z"}}, {"condition": {"id": 1569}, "defaults": {"site_id": 66, "file_path": "LOGO_KECIl_copy.png", "jenis": "logo-top", "created_at": "2022-01-11T13:21:12.667Z", "updated_at": "2022-01-11T13:34:50.594Z"}}, {"condition": {"id": 1570}, "defaults": {"site_id": 66, "file_path": "Header_copy.jpg", "jenis": "banner-top", "created_at": "2022-01-11T13:36:35.403Z", "updated_at": "2022-01-11T13:36:35.403Z"}}, {"condition": {"id": 1571}, "defaults": {"site_id": 66, "file_path": "LOGO_KECIl_copybawah.png", "jenis": "logo-bottom", "created_at": "2022-01-11T13:40:48.925Z", "updated_at": "2022-01-11T13:40:48.925Z"}}, {"condition": {"id": 1572}, "defaults": {"site_id": 66, "file_path": "ucapan_-_Copy_copy.jpg", "jenis": "highlight1", "created_at": "2022-01-11T13:46:12.196Z", "updated_at": "2022-01-11T13:46:12.196Z"}}, {"condition": {"id": 1573}, "defaults": {"site_id": 66, "file_path": "ucapan_copy.jpg", "jenis": "highlight1", "created_at": "2022-01-11T13:47:23.601Z", "updated_at": "2022-01-11T13:47:23.601Z"}}, {"condition": {"id": 1574}, "defaults": {"site_id": 66, "file_path": "271734962_252568197016128_1361125772276388212_n.jpg", "jenis": "highlight1", "created_at": "2022-01-11T14:07:48.156Z", "updated_at": "2022-01-11T14:07:48.156Z"}}, {"condition": {"id": 1575}, "defaults": {"site_id": 66, "file_path": "271540362_252236943715920_3609344185063427408_n.jpg", "jenis": "highlight1", "created_at": "2022-01-11T14:09:47.624Z", "updated_at": "2022-01-11T14:09:47.624Z"}}, {"condition": {"id": 1576}, "defaults": {"site_id": 66, "file_path": "271341998_250803480525933_7520547808129206744_n.jpg", "jenis": "highlight1", "created_at": "2022-01-11T14:11:37.240Z", "updated_at": "2022-01-11T14:11:37.240Z"}}, {"condition": {"id": 1579}, "defaults": {"site_id": 66, "file_path": "926e2b01-5a02-4204-be04-59e0aacc4bc7.jpg", "jenis": "pejabat-opd", "created_at": "2022-01-12T10:20:06.883Z", "updated_at": "2022-01-12T10:20:06.883Z"}}, {"condition": {"id": 1580}, "defaults": {"site_id": 66, "file_path": "271626472_252848643654750_1607886224352111295_n.jpg", "jenis": "highlight1", "created_at": "2022-01-12T10:36:03.119Z", "updated_at": "2022-01-12T10:36:03.119Z"}}, {"condition": {"id": 1581}, "defaults": {"site_id": 66, "file_path": "271777835_252787676994180_1706597214092193931_n.jpg", "jenis": "highlight1", "created_at": "2022-01-12T10:37:30.501Z", "updated_at": "2022-01-12T10:37:30.502Z"}}, {"condition": {"id": 1582}, "defaults": {"site_id": 66, "file_path": "271347078_252783100327971_712561639600783987_n.jpg", "jenis": "highlight1", "created_at": "2022-01-12T10:38:42.047Z", "updated_at": "2022-01-12T10:38:42.047Z"}}, {"condition": {"id": 1583}, "defaults": {"site_id": 66, "file_path": "271314434_252700993669515_9111433118181424871_n.jpg", "jenis": "highlight1", "created_at": "2022-01-12T10:40:36.465Z", "updated_at": "2022-01-12T10:40:36.465Z"}}, {"condition": {"id": 1589}, "defaults": {"site_id": 66, "file_path": "271651173_253476733591941_8779663535195298668_n.jpg", "jenis": "highlight1", "created_at": "2022-01-14T14:50:59.325Z", "updated_at": "2022-01-14T14:52:02.582Z"}}, {"condition": {"id": 1590}, "defaults": {"site_id": 66, "file_path": "0f9553d7-9751-4184-9048-8500a641b037.jfif", "jenis": "highlight1", "created_at": "2022-01-14T14:53:12.805Z", "updated_at": "2022-01-14T14:53:12.805Z"}}, {"condition": {"id": 1591}, "defaults": {"site_id": 66, "file_path": "271887706_256129679993313_6577705556686236665_n.jpg", "jenis": "highlight1", "created_at": "2022-01-17T10:32:21.791Z", "updated_at": "2022-01-17T10:32:21.791Z"}}]