[{"condition": {"id": 25}, "defaults": {"site_id": 31, "photo_id": 105, "link": "", "position": "top", "created_at": "2021-05-28T14:59:03.337Z", "updated_at": "2023-11-03T02:47:17.928Z"}}, {"condition": {"id": 26}, "defaults": {"site_id": 31, "photo_id": 106, "link": "", "position": "bottom", "created_at": "2021-05-28T14:59:21.392Z", "updated_at": "2023-11-03T02:47:28.896Z"}}, {"condition": {"id": 27}, "defaults": {"site_id": 31, "photo_id": 107, "link": "", "position": "middle1", "created_at": "2021-05-28T14:59:40.158Z", "updated_at": "2021-05-28T14:59:40.158Z"}}, {"condition": {"id": 76}, "defaults": {"site_id": 31, "photo_id": 341, "link": "https://www.lapor.go.id/instansi/pemerintah-kabupaten-lombok-barat", "position": "middle2", "created_at": "2021-06-08T09:33:47.463Z", "updated_at": "2021-06-08T21:30:20.364Z"}}]