[{"condition": {"id": 854}, "defaults": {"site_id": 62, "admin_id": 80, "file_path": "hasil_data_grafik_statistik_pasien.xlsx", "nama": "Statistis Pasien 2023", "deskripsi": null, "size": 17356, "hits": 0, "created_at": "2024-07-25T00:11:44.852Z", "updated_at": "2024-07-25T00:11:45.063Z", "status": "published"}}, {"condition": {"id": 855}, "defaults": {"site_id": 62, "admin_id": 80, "file_path": "Grafik_Kunjungan_Pasien.pdf", "nama": "Kunjungan Pasien 2023", "deskripsi": null, "size": 72727, "hits": 0, "created_at": "2024-07-25T00:12:04.443Z", "updated_at": "2024-07-25T00:12:04.597Z", "status": "published"}}, {"condition": {"id": 856}, "defaults": {"site_id": 62, "admin_id": 80, "file_path": "Grafik_Penyakit_Terbanyak.pdf", "nama": "Penyakit Terbanyak 2023", "deskripsi": null, "size": 79544, "hits": 0, "created_at": "2024-07-25T00:13:13.690Z", "updated_at": "2024-07-25T00:13:13.790Z", "status": "published"}}]